single_cycle.v
module adder(a,b,y);
    input [31:0] a, b;
    output [31:0] y;
    assign y = a + b;
endmodule


module Mux_2x1 (I0,I1,s,out);

    input [31:0]I0,I1;
    input s;
    output [31:0]out;

    assign out= (s) ? I1 : I0;
    
endmodule

module Mux_4x1(I0,I1,I2,s,out);
    input [31:0] I0,I1,I2;
    input [1:0] s;
    output [31:0] out;
    assign out = (s == 2'b00) ? I0:
                    (s == 2'b01) ? I1: I2;
                 
endmodule


module ALU (aluControl,a,b,result,zero);
    input [2:0] aluControl;
    input [31:0] a;
    input [31:0] b;
    output reg [31:0] result;
    output  zero;

    always @(*)
    begin
        case(aluControl)
            3'b000: result = a + b;  
            3'b001: result = a - b;   
            3'b010: result = a & b;   
            3'b011: result = a | b; 
            3'b100:result = a >>> b[5:0];  
            3'b101: result = (a < b) ? 32'b00000000000000000000000000000001 : 32'b00000000000000000000000000000000;
            default: result = 32'h00000000;
        endcase
       
    end
    assign zero = &(~result);
endmodule



module PC (PCNext,clk,rst,PC);
    input [31:0] PCNext;
    input clk,rst;
    output reg [31:0] PC;
    always @(posedge clk)
    begin
        if(~rst)
            PC <= {32{1'b0}};
        else
            PC <= PCNext;
    end
endmodule

module PC_Adder (PC,PCPlus4);

    input [31:0]PC;
    output [31:0]PCPlus4;

    assign PCPlus4 = PC + 32'h4;
    
endmodule


module Instruction_Memory ( rst, A, RD);

    input rst;
    input [31:0] A;
    output  [31:0] RD;
    reg [31:0] mem [1023:0];

    assign RD = (~rst) ? {32{1'b0}} : mem[A[31:2]];
    // result[count[i]] = arr[i]
    initial begin
        mem[0] = 32'h00000413;// addi s0, zero, 0x00000000  // arr dizisinin başlangıç adresi    
        mem[1] = 32'h05000493; // addi s1, zero, 0x00000050  // count dizisinin başlangıç adresi
        mem[2] = 32'h0A000993; // addi s3, zero, 0x000000A0  // result dizisinin başlangıç adresi
        mem[3] = 32'h00000913; // addi s2, zero, 0  // Döngü değişkeni (i) 
        mem[4] = 32'h01400293; //addi t0, zero, 20 // dizi boyutu
        mem[5] = 32'h00048393; //addi t2,s1,0 // t2 = count adresini 
        mem[6] = 32'h00080F93;// addi t6,s0,0 // arr adresi
        mem[7] = 32'h02590663;// for:beq s2, t0, end_loop // Döngü değişkeni (i) dizinin boyutuna eşitse döngüden çık
        mem[8] = 32'h0003AE83; //lw t4, 0(t2)// count dizisinin i. elemanını yükle
        mem[9] = 32'h000FA303;//lw t1,0(t6) // arr dizisinin i.elemanını yukle 
        mem[10] = 32'h004F8F93;//addi t6,t6,4 // arr adresini bir sonrakine tasi
        mem[11] = 32'h00438393; //addi t2, t2, 4// count adresini bir sonraki elemana taşı
        mem[12] = 32'h00190913;//addi s2, s2, 1// i = i + 1
        mem[13] = 32'h01DE8EB3;//add t4,t4,t4 
        mem[14] = 32'h01DE8EB3;//add t4,t4,t4
        mem[15] = 32'h01D98F33;//add t5,s3,t4 // result+ t4 adresi
        mem[16] =32'h006F2023;//sw t1,0(t5) // arr in i.değerini bu adrese at 
        mem[17] =32'hFD9FF0EF;//jal ra for // Döngüye geri dön    -36 olmalı


    end
    endmodule



module register_file(
    input clk, rst, WE3,
    input [4:0] A1, A2, A3,
    input [31:0] WD3,
    output [31:0] RD1, RD2
);

    reg [31:0] Register [31:0]; 

    always @(posedge clk) begin
        if (~rst) begin
            for (integer i = 0; i < 32; i = i + 1) begin
                Register[i] <= 32'h00000000;
            end
        end
        
    end
    
    always @ (posedge clk)
    begin
        if(WE3)
            Register[A3] <= WD3;
    end
    
    
    assign RD1 = (~rst) ? 32'd0 : Register[A1];
    assign RD2 = (~rst) ? 32'd0 : Register[A2];

endmodule



module ALU_Decoder(ALUOp,funct3,funct7,op,ALUControl);
    input [1:0] ALUOp;
    input [2:0] funct3;
    input [6:0] funct7;
    input [6:0] op; 
    output [2:0] ALUControl;

    wire [2:0] ALUControl_Logic;
    assign ALUControl = (ALUOp == 2'b00) ? 3'b000 :
                        (ALUOp == 2'b01) ? 3'b001 :
                        (ALUOp == 2'b10) ? ALUControl_Logic : 3'bxxx;

    

    assign ALUControl_Logic = (funct3 == 3'b000) ? 
                                    ({op[5], funct7[5]} == 2'b11 ? 3'b001 : 3'b000) :
                                    (funct3 == 3'b010) ? 3'b101 :
                                    (funct3 == 3'b110) ? 3'b011 :
                                    (funct3 == 3'b111) ? 3'b010 :
                                    (funct3 == 3'b101) ? 3'b100 : 
                                    3'b000;

endmodule




module Main_Decoder(Op,RegWrite,ImmSrc,ALUSrc,MemWrite,ResultSrc,Branch,Jump,ALUOp,zero,PCSrc);
    input [6:0]Op;
    input zero; 
    output RegWrite,ALUSrc,MemWrite,Branch,Jump,PCSrc;
    output [1:0]ImmSrc,ALUOp,ResultSrc;


    assign RegWrite = (Op == 7'b0000011 | Op == 7'b0110011 | Op == 7'b0010011 | Op == 7'b1101111) ? 1'b1 :1'b0 ;

    assign ImmSrc = (Op == 7'b0000011 | Op == 7'b0010011) ? 2'b00 : 
                    (Op == 7'b0100011) ? 2'b01 :
                    (Op == 7'b1100011) ? 2'b10 : 2'b11  ;                     

    assign ALUSrc = (Op == 7'b0000011 | Op == 7'b0100011 | Op == 7'b0010011) ? 1'b1 : 1'b0 ;

    assign MemWrite = (Op == 7'b0100011) ? 1'b1 :1'b0 ;

    assign ResultSrc = (Op == 7'b0000011) ? 2'b01 :
                        (Op == 7'b0110011 | Op == 7'b0010011) ? 2'b00 : 2'b10 ;

    assign Branch = (Op == 7'b1100011) ? 1'b1 :1'b0 ;

    assign Jump = (Op == 7'b1101111) ? 1'b1:1'b0;

    assign PCSrc = (zero & Branch) | Jump;
    assign ALUOp = (Op == 7'b0000011 | Op == 7'b0100011) ? 2'b00 :
                    (Op == 7'b0110011 | Op == 7'b0010011) ? 2'b10 : 2'b01 ;

endmodule

module Control_Unit(Op,RegWrite,ImmSrc,ALUSrc,MemWrite,ResultSrc,Branch,Jump,funct3,funct7,ALUControl,zero,PCSrc);

    input [6:0]Op,funct7;
    input [2:0]funct3;
    input zero;
    output RegWrite,ALUSrc,MemWrite,Jump,Branch;
    output [1:0]ImmSrc,ResultSrc;
    output [2:0]ALUControl;
    output PCSrc;

    wire [1:0]ALUOp;

    Main_Decoder Main_Decoder(
                .Op(Op),
                .RegWrite(RegWrite),
                .ImmSrc(ImmSrc),
                .MemWrite(MemWrite),
                .ResultSrc(ResultSrc),
                .Branch(Branch),
                .Jump(Jump),
                .ALUSrc(ALUSrc),
                .ALUOp(ALUOp),
                .zero(zero),
                .PCSrc(PCSrc)
    );

    ALU_Decoder ALU_Decoder(
                            .ALUOp(ALUOp),
                            .funct3(funct3),
                            .funct7(funct7),
                            .op(Op),
                            .ALUControl(ALUControl)
    );


endmodule

module Data_Memory(clk,rst,WE,WD,A,RD);

    input clk,rst,WE;
    input [31:0]A,WD;
    output [31:0]RD;

    reg [31:0] mem [1023:0];

    always @ (posedge clk)
    begin
        if(WE)
            mem[A[31:2]] <= WD;
    end

    assign RD = (~rst) ? 32'd0 : mem[A[31:2]];
    
    
    

    initial begin
        // arr
        mem[0] = 32'h00000003;
        mem[1] = 32'h00000007;
        mem[2] = 32'h00000002;
        mem[3] = 32'h00000006;
        mem[4] = 32'h00000005;
        mem[5] = 32'h00000004;
        mem[6] = 32'h00000001;
        mem[7] = 32'h000003E8;
        mem[8] = 32'h000003E7;
        mem[9] = 32'h00000019;
        mem[10] = 32'h0000005A;
        mem[11] = 32'h00000064;
        mem[12] = 32'h0000001E;
        mem[13] = 32'h00000014;
        mem[14] = 32'h0000000A;
        mem[15] = 32'h000000C8;
        mem[16] = 32'h00000CE4;
        mem[17] = 32'h000000FA;
        mem[18] = 32'h0000000C;
        mem[19] = 32'h0000004B;
        //count
        mem[20] = 32'h00000011;
        mem[21] = 32'h0000000D;
        mem[22] = 32'h00000012;
        mem[23] = 32'h0000000E;
        mem[24] = 32'h0000000F;
        mem[25] = 32'h00000010;
        mem[26] = 32'h00000013;
        mem[27] = 32'h00000001;
        mem[28] = 32'h00000002;
        mem[29] = 32'h00000009;
        mem[30] = 32'h00000006;
        mem[31] = 32'h00000005;
        mem[32] = 32'h00000008;
        mem[33] = 32'h0000000A;
        mem[34] = 32'h0000000C;
        mem[35] = 32'h00000004;
        mem[36] = 32'h00000000;
        mem[37] = 32'h00000003;
        mem[38] = 32'h0000000B;
        mem[39] = 32'h00000007;
       


    end
    always @(posedge clk) begin
        if (~rst) begin
            for (integer i = 40; i < 60; i = i + 1) begin
                mem[i] <= 32'h00000000;
            end
        end
        
    end



endmodule


module Sign_Extend (input [31:0] Instr, input [1:0] ImmSrc, output reg [31:0] Imm_Ext);
    always @*
    begin
        case (ImmSrc)
            2'b00: Imm_Ext = {{20{Instr[31]}}, Instr[31:20]};
            2'b01: Imm_Ext = {{20{Instr[31]}}, Instr[31:25], Instr[11:7]};
            2'b10: Imm_Ext = {{20{Instr[31]}}, Instr[7], Instr[30:25], Instr[11:8], 1'b0};
            2'b11: Imm_Ext = {{12{Instr[31]}}, Instr[19:12], Instr[20], Instr[30:21], 1'b0};
            default: Imm_Ext = 32'b0; 
        endcase;
    end
endmodule



module single_cycle(clk, rst);
    input clk, rst;
    wire [31:0] PC, PCNext, RD_Instr, RD1, RD2, ImmExt, ALUResult, ReadData, PCTarget, PCPlus4, SrcB, Result;
    wire RegWrite, MemWrite, ALUSrc, Branch, Jump, PCSrc,zero;
    wire [1:0] ResultSrc, ImmSrc, AluOp;
    wire [2:0] AluControl;

    PC PC_inst(
        .PCNext(PCNext),
        .clk(clk),
        .rst(rst),
        .PC(PC)
    );

    PC_Adder PC_adder(
        .PC(PC),
        .PCPlus4(PCPlus4)
    );
    adder PC_Target_adder(
        .a(PC),
        .b(ImmExt),
        .y(PCTarget)
    );

    Mux_2x1 PCMUX(
        .I0(PCPlus4),
        .I1(PCTarget),
        .s(PCSrc),
        .out(PCNext)
    );

    Instruction_Memory Instruction_Memory(
        .rst(rst),
        .A(PC),
        .RD(RD_Instr)
    );

    register_file Register_File(
        .clk(clk),
        .rst(rst),
        .WE3(RegWrite),
        .WD3(Result),
        .A1(RD_Instr[19:15]),
        .A2(RD_Instr[24:20]),
        .A3(RD_Instr[11:7]),
        .RD1(RD1),
        .RD2(RD2)
    );

    Sign_Extend Sign_Extend(
        .Instr(RD_Instr),
        .ImmSrc(ImmSrc),
        .Imm_Ext(ImmExt)
    );


     Mux_2x1 MuxRegister_ALU(
        .I0(RD2),
        .I1(ImmExt),
        .s(ALUSrc),
        .out(SrcB)
    );

     ALU ALU(
            .aluControl(AluControl),
            .a(RD1),
            .b(SrcB),
            .result(ALUResult),
            .zero(zero)
    );

    Control_Unit ControlUnit(
        .Op(RD_Instr[6:0]),
        .RegWrite(RegWrite),
        .ImmSrc(ImmSrc),
        .ALUSrc(ALUSrc),
        .MemWrite(MemWrite),
        .ResultSrc(ResultSrc),
        .Branch(Branch),
        .Jump(Jump),
        .PCSrc(PCSrc),
        .funct3(RD_Instr[14:12]),
        .funct7(RD_Instr[31:25]),
        .zero(zero),
        .ALUControl(AluControl)
    );

     Data_Memory Data_Memory(
        .clk(clk),
        .rst(rst),
        .WE(MemWrite),
        .WD(RD2),
        .A(ALUResult),
        .RD(ReadData)
    );

    Mux_4x1 MUXDataMemory_Register(
        .I0(ALUResult),
        .I1(ReadData),
        .I2(PCPlus4),
        .s(ResultSrc),
        .out(Result)
    );

endmodule

test_bench.v
`include "single_cycle.v"
module single_cycle_tb();

    reg clk=1'b1,rst = 1'b0;

    single_cycle Single_Cycle(
        .clk(clk),
        .rst(rst)
    );

    
    initial begin
        $dumpfile("Single Cycle.vcd");
        $dumpvars(0,single_cycle_tb);
        // To view the ordered array in GTKWave.
        // for (integer i = 40; i < 60; i = i + 1) begin
        //     $dumpvars(0, Single_Cycle.Data_Memory.mem[i]);
        // end
    
    end

    always 
    begin
        clk = ~ clk;
        #10;      
    end
    initial
    begin
        // rst <= 1'b0;
        // #50;

        rst <=1'b1;
        #5000; // 2460? dene kontrol et tek tek hepsini 
        
        #5
        for(integer i = 40; i < 60; i = i + 1) begin
            $display("Memory[%0d] = %d", i, Single_Cycle.Data_Memory.mem[i]);
        end
        #5
        
        $finish;
    end
    

endmodule

Single Cycle.vcd
$date
	Tue Jun 04 20:53:01 2024
$end
$version
	Icarus Verilog
$end
$timescale
	1s
$end
$scope module single_cycle_tb $end
$var reg 1 ! clk $end
$var reg 1 " rst $end
$scope module Single_Cycle $end
$var wire 1 ! clk $end
$var wire 1 " rst $end
$var wire 1 # zero $end
$var wire 32 $ SrcB [31:0] $end
$var wire 2 % ResultSrc [1:0] $end
$var wire 32 & Result [31:0] $end
$var wire 1 ' RegWrite $end
$var wire 32 ( ReadData [31:0] $end
$var wire 32 ) RD_Instr [31:0] $end
$var wire 32 * RD2 [31:0] $end
$var wire 32 + RD1 [31:0] $end
$var wire 32 , PCTarget [31:0] $end
$var wire 1 - PCSrc $end
$var wire 32 . PCPlus4 [31:0] $end
$var wire 32 / PCNext [31:0] $end
$var wire 32 0 PC [31:0] $end
$var wire 1 1 MemWrite $end
$var wire 1 2 Jump $end
$var wire 2 3 ImmSrc [1:0] $end
$var wire 32 4 ImmExt [31:0] $end
$var wire 1 5 Branch $end
$var wire 3 6 AluControl [2:0] $end
$var wire 1 7 ALUSrc $end
$var wire 32 8 ALUResult [31:0] $end
$scope module ALU $end
$var wire 1 # zero $end
$var wire 32 9 b [31:0] $end
$var wire 3 : aluControl [2:0] $end
$var wire 32 ; a [31:0] $end
$var reg 32 < result [31:0] $end
$upscope $end
$scope module ControlUnit $end
$var wire 7 = Op [6:0] $end
$var wire 3 > funct3 [2:0] $end
$var wire 7 ? funct7 [6:0] $end
$var wire 1 # zero $end
$var wire 2 @ ResultSrc [1:0] $end
$var wire 1 ' RegWrite $end
$var wire 1 - PCSrc $end
$var wire 1 1 MemWrite $end
$var wire 1 2 Jump $end
$var wire 2 A ImmSrc [1:0] $end
$var wire 1 5 Branch $end
$var wire 1 7 ALUSrc $end
$var wire 2 B ALUOp [1:0] $end
$var wire 3 C ALUControl [2:0] $end
$scope module ALU_Decoder $end
$var wire 3 D funct3 [2:0] $end
$var wire 7 E funct7 [6:0] $end
$var wire 7 F op [6:0] $end
$var wire 2 G ALUOp [1:0] $end
$var wire 3 H ALUControl_Logic [2:0] $end
$var wire 3 I ALUControl [2:0] $end
$upscope $end
$scope module Main_Decoder $end
$var wire 7 J Op [6:0] $end
$var wire 1 - PCSrc $end
$var wire 1 # zero $end
$var wire 2 K ResultSrc [1:0] $end
$var wire 1 ' RegWrite $end
$var wire 1 1 MemWrite $end
$var wire 1 2 Jump $end
$var wire 2 L ImmSrc [1:0] $end
$var wire 1 5 Branch $end
$var wire 1 7 ALUSrc $end
$var wire 2 M ALUOp [1:0] $end
$upscope $end
$upscope $end
$scope module Data_Memory $end
$var wire 32 N A [31:0] $end
$var wire 1 1 WE $end
$var wire 1 ! clk $end
$var wire 1 " rst $end
$var wire 32 O WD [31:0] $end
$var wire 32 P RD [31:0] $end
$scope begin $ivl_for_loop1 $end
$var integer 32 Q i [31:0] $end
$upscope $end
$upscope $end
$scope module Instruction_Memory $end
$var wire 1 " rst $end
$var wire 32 R RD [31:0] $end
$var wire 32 S A [31:0] $end
$upscope $end
$scope module MUXDataMemory_Register $end
$var wire 32 T I0 [31:0] $end
$var wire 32 U I1 [31:0] $end
$var wire 2 V s [1:0] $end
$var wire 32 W out [31:0] $end
$var wire 32 X I2 [31:0] $end
$upscope $end
$scope module MuxRegister_ALU $end
$var wire 1 7 s $end
$var wire 32 Y out [31:0] $end
$var wire 32 Z I1 [31:0] $end
$var wire 32 [ I0 [31:0] $end
$upscope $end
$scope module PCMUX $end
$var wire 1 - s $end
$var wire 32 \ out [31:0] $end
$var wire 32 ] I1 [31:0] $end
$var wire 32 ^ I0 [31:0] $end
$upscope $end
$scope module PC_Target_adder $end
$var wire 32 _ y [31:0] $end
$var wire 32 ` b [31:0] $end
$var wire 32 a a [31:0] $end
$upscope $end
$scope module PC_adder $end
$var wire 32 b PCPlus4 [31:0] $end
$var wire 32 c PC [31:0] $end
$upscope $end
$scope module PC_inst $end
$var wire 32 d PCNext [31:0] $end
$var wire 1 ! clk $end
$var wire 1 " rst $end
$var reg 32 e PC [31:0] $end
$upscope $end
$scope module Register_File $end
$var wire 5 f A1 [4:0] $end
$var wire 5 g A2 [4:0] $end
$var wire 5 h A3 [4:0] $end
$var wire 32 i WD3 [31:0] $end
$var wire 1 ' WE3 $end
$var wire 1 ! clk $end
$var wire 1 " rst $end
$var wire 32 j RD2 [31:0] $end
$var wire 32 k RD1 [31:0] $end
$scope begin $ivl_for_loop0 $end
$var integer 32 l i [31:0] $end
$upscope $end
$upscope $end
$scope module Sign_Extend $end
$var wire 2 m ImmSrc [1:0] $end
$var wire 32 n Instr [31:0] $end
$var reg 32 o Imm_Ext [31:0] $end
$upscope $end
$upscope $end
$scope begin $ivl_for_loop2 $end
$var integer 32 p i [31:0] $end
$upscope $end
$upscope $end
$enddefinitions $end
$comment Show the parameter values. $end
$dumpall
$end
#0
$dumpvars
bx p
b0 o
b10000010011 n
b0 m
b100000 l
b0 k
b0 j
b0 i
b1000 h
b0 g
b0 f
b0 e
b100 d
b0 c
b100 b
b0 a
b0 `
b0 _
b100 ^
b0 ]
b100 \
b0 [
b0 Z
b0 Y
b100 X
b0 W
b0 V
b11 U
b0 T
b0 S
b10000010011 R
b111100 Q
b11 P
b0 O
b0 N
b10 M
b0 L
b0 K
b10011 J
b0 I
b0 H
b10 G
b10011 F
b0 E
b0 D
b0 C
b10 B
b0 A
b0 @
b0 ?
b0 >
b10011 =
b0 <
b0 ;
b0 :
b0 9
b0 8
17
b0 6
05
b0 4
b0 3
02
01
b0 0
b100 /
b100 .
0-
b0 ,
b0 +
b0 *
b10000010011 )
b11 (
1'
b0 &
b0 %
b0 $
1#
1"
0!
$end
#10
b10001 (
b10001 P
b10001 U
b1010000 &
b1010000 W
b1010000 i
0#
b1010000 8
b1010000 <
b1010000 N
b1010000 T
b1010000 $
b1010000 9
b1010000 Y
b10 ?
b10 E
b1001 h
b10000 g
b1010000 4
b1010000 Z
b1010000 `
b1010000 o
b101000000000000010010010011 )
b101000000000000010010010011 R
b101000000000000010010010011 n
b1000 /
b1000 \
b1000 d
b1000 .
b1000 X
b1000 ^
b1000 b
b1010100 ,
b1010100 ]
b1010100 _
b100 0
b100 S
b100 a
b100 c
b100 e
1!
#20
0!
#30
b0 (
b0 P
b0 U
b10100000 &
b10100000 W
b10100000 i
b10100000 8
b10100000 <
b10100000 N
b10100000 T
b10100000 $
b10100000 9
b10100000 Y
b101 ?
b101 E
b10011 h
b0 g
b10100000 4
b10100000 Z
b10100000 `
b10100000 o
b1010000000000000100110010011 )
b1010000000000000100110010011 R
b1010000000000000100110010011 n
b1100 /
b1100 \
b1100 d
b1100 .
b1100 X
b1100 ^
b1100 b
b10101000 ,
b10101000 ]
b10101000 _
b1000 0
b1000 S
b1000 a
b1000 c
b1000 e
1!
#40
0!
#50
b11 (
b11 P
b11 U
b0 &
b0 W
b0 i
1#
b0 8
b0 <
b0 N
b0 T
b0 $
b0 9
b0 Y
b0 ?
b0 E
b10010 h
b0 4
b0 Z
b0 `
b0 o
b100100010011 )
b100100010011 R
b100100010011 n
b10000 /
b10000 \
b10000 d
b10000 .
b10000 X
b10000 ^
b10000 b
b1100 ,
b1100 ]
b1100 _
b1100 0
b1100 S
b1100 a
b1100 c
b1100 e
1!
#60
0!
#70
b100 (
b100 P
b100 U
b10100 &
b10100 W
b10100 i
0#
b10100 8
b10100 <
b10100 N
b10100 T
b10100 $
b10100 9
b10100 Y
b101 h
b10100 g
b10100 4
b10100 Z
b10100 `
b10100 o
b1010000000000001010010011 )
b1010000000000001010010011 R
b1010000000000001010010011 n
b10100 /
b10100 \
b10100 d
b10100 .
b10100 X
b10100 ^
b10100 b
b100100 ,
b100100 ]
b100100 _
b10000 0
b10000 S
b10000 a
b10000 c
b10000 e
1!
#80
0!
#90
b10001 (
b10001 P
b10001 U
b1010000 &
b1010000 W
b1010000 i
b1010000 8
b1010000 <
b1010000 N
b1010000 T
b1010000 +
b1010000 ;
b1010000 k
b0 $
b0 9
b0 Y
b111 h
b0 g
b1001 f
b0 4
b0 Z
b0 `
b0 o
b1001000001110010011 )
b1001000001110010011 R
b1001000001110010011 n
b11000 /
b11000 \
b11000 d
b11000 .
b11000 X
b11000 ^
b11000 b
b10100 ,
b10100 ]
b10100 _
b10100 0
b10100 S
b10100 a
b10100 c
b10100 e
1!
#100
0!
#110
b11 (
b11 P
b11 U
b0 &
b0 W
b0 i
1#
b0 8
b0 <
b0 N
b0 T
b0 +
b0 ;
b0 k
b11111 h
b10000 f
b10000000111110010011 )
b10000000111110010011 R
b10000000111110010011 n
b11100 /
b11100 \
b11100 d
b11100 .
b11100 X
b11100 ^
b11100 b
b11000 ,
b11000 ]
b11000 _
b11000 0
b11000 S
b11000 a
b11000 c
b11000 e
1!
#120
0!
#130
b1 6
b1 :
b1 C
b1 I
bx (
bx P
bx U
0'
b10 %
b10 @
b10 K
b10 V
0-
b1 B
b1 G
b1 M
b100000 &
b100000 W
b100000 i
0#
b10 3
b10 A
b10 L
b10 m
07
b11111111111111111111111111101100 8
b11111111111111111111111111101100 <
b11111111111111111111111111101100 N
b11111111111111111111111111101100 T
15
b10100 *
b10100 O
b10100 [
b10100 j
b10100 $
b10100 9
b10100 Y
b1 ?
b1 E
b1100011 =
b1100011 F
b1100011 J
b1100 h
b101 g
b10010 f
b101100 4
b101100 Z
b101100 `
b101100 o
b10010110010000011001100011 )
b10010110010000011001100011 R
b10010110010000011001100011 n
b100000 /
b100000 \
b100000 d
b100000 .
b100000 X
b100000 ^
b100000 b
b1001000 ,
b1001000 ]
b1001000 _
b11100 0
b11100 S
b11100 a
b11100 c
b11100 e
1!
#140
0!
#150
1'
b10001 (
b10001 P
b10001 U
17
b0 6
b0 :
b0 C
b0 I
b0 3
b0 A
b0 L
b0 m
b0 B
b0 G
b0 M
b0 $
b0 9
b0 Y
b1010000 8
b1010000 <
b1010000 N
b1010000 T
b101 H
b1 %
b1 @
b1 K
b1 V
05
b0 *
b0 O
b0 [
b0 j
b1010000 +
b1010000 ;
b1010000 k
b0 ?
b0 E
b10 >
b10 D
b11 =
b11 F
b11 J
b11101 h
b0 g
b111 f
b0 4
b0 Z
b0 `
b0 o
b10001 &
b10001 W
b10001 i
b111010111010000011 )
b111010111010000011 R
b111010111010000011 n
b100100 /
b100100 \
b100100 d
b100100 .
b100100 X
b100100 ^
b100100 b
b100000 ,
b100000 ]
b100000 _
b100000 0
b100000 S
b100000 a
b100000 c
b100000 e
1!
#160
0!
#170
b11 &
b11 W
b11 i
b11 (
b11 P
b11 U
1#
b0 8
b0 <
b0 N
b0 T
b0 +
b0 ;
b0 k
b110 h
b11111 f
b11111010001100000011 )
b11111010001100000011 R
b11111010001100000011 n
b101000 /
b101000 \
b101000 d
b101000 .
b101000 X
b101000 ^
b101000 b
b100100 ,
b100100 ]
b100100 _
b100100 0
b100100 S
b100100 a
b100100 c
b100100 e
1!
#180
0!
#190
b111 (
b111 P
b111 U
b100 &
b100 W
b100 i
b0 6
b0 :
b0 C
b0 I
0#
b10 B
b10 G
b10 M
b100 8
b100 <
b100 N
b100 T
b0 H
b0 %
b0 @
b0 K
b0 V
b100 $
b100 9
b100 Y
b0 >
b0 D
b10011 =
b10011 F
b10011 J
b11111 h
b100 g
b100 4
b100 Z
b100 `
b100 o
b10011111000111110010011 )
b10011111000111110010011 R
b10011111000111110010011 n
b101100 /
b101100 \
b101100 d
b101100 .
b101100 X
b101100 ^
b101100 b
b101100 ,
b101100 ]
b101100 _
b101000 0
b101000 S
b101000 a
b101000 c
b101000 e
1!
#200
0!
#210
b1101 (
b1101 P
b1101 U
b1010100 &
b1010100 W
b1010100 i
b111 h
b111 f
b1010100 8
b1010100 <
b1010100 N
b1010100 T
b10000111000001110010011 )
b10000111000001110010011 R
b10000111000001110010011 n
b1010000 +
b1010000 ;
b1010000 k
b110000 /
b110000 \
b110000 d
b110000 .
b110000 X
b110000 ^
b110000 b
b110000 ,
b110000 ]
b110000 _
b101100 0
b101100 S
b101100 a
b101100 c
b101100 e
1!
#220
0!
#230
b1 $
b1 9
b1 Y
b11 (
b11 P
b11 U
b10010 h
b1 g
b10010 f
b1 4
b1 Z
b1 `
b1 o
b1 &
b1 W
b1 i
b110010000100100010011 )
b110010000100100010011 R
b110010000100100010011 n
b1 8
b1 <
b1 N
b1 T
b110100 /
b110100 \
b110100 d
b0 +
b0 ;
b0 k
b110100 .
b110100 X
b110100 ^
b110100 b
b110001 ,
b110001 ]
b110001 _
b110000 0
b110000 S
b110000 a
b110000 c
b110000 e
1!
#240
0!
#250
b1111100111 (
b1111100111 P
b1111100111 U
1'
b11 3
b11 A
b11 L
b11 m
07
b10001 *
b10001 O
b10001 [
b10001 j
b10001 $
b10001 9
b10001 Y
b100010 &
b100010 W
b100010 i
b110011 =
b110011 F
b110011 J
b11101 h
b11101 g
b11101 f
b11101000100000011100 4
b11101000100000011100 Z
b11101000100000011100 `
b11101000100000011100 o
b100010 8
b100010 <
b100010 N
b100010 T
b1110111101000111010110011 )
b1110111101000111010110011 R
b1110111101000111010110011 n
b10001 +
b10001 ;
b10001 k
b111000 /
b111000 \
b111000 d
b111000 .
b111000 X
b111000 ^
b111000 b
b11101000100001010000 ,
b11101000100001010000 ]
b11101000100001010000 _
b110100 0
b110100 S
b110100 a
b110100 c
b110100 e
1!
#260
0!
#270
b11111010 (
b11111010 P
b11111010 U
b1000100 &
b1000100 W
b1000100 i
b1000100 8
b1000100 <
b1000100 N
b1000100 T
b100010 $
b100010 9
b100010 Y
b111100 /
b111100 \
b111100 d
b100010 +
b100010 ;
b100010 k
b100010 *
b100010 O
b100010 [
b100010 j
b111100 .
b111100 X
b111100 ^
b111100 b
b11101000100001010100 ,
b11101000100001010100 ]
b11101000100001010100 _
b111000 0
b111000 S
b111000 a
b111000 c
b111000 e
1!
#280
0!
#290
b0 (
b0 P
b0 U
b11100100 &
b11100100 W
b11100100 i
b11110 h
b10011 f
b10011000100000011100 4
b10011000100000011100 Z
b10011000100000011100 `
b10011000100000011100 o
b11100100 8
b11100100 <
b11100100 N
b11100100 T
b1000100 $
b1000100 9
b1000100 Y
b1110110011000111100110011 )
b1110110011000111100110011 R
b1110110011000111100110011 n
b10100000 +
b10100000 ;
b10100000 k
b1000100 *
b1000100 O
b1000100 [
b1000100 j
b1000000 /
b1000000 \
b1000000 d
b1000000 .
b1000000 X
b1000000 ^
b1000000 b
b10011000100001011000 ,
b10011000100001011000 ]
b10011000100001011000 _
b111100 0
b111100 S
b111100 a
b111100 c
b111100 e
1!
#300
0!
#310
0'
b0 (
b0 P
b0 U
17
b10 %
b10 @
b10 K
b10 V
b1000100 &
b1000100 W
b1000100 i
b1 3
b1 A
b1 L
b1 m
b0 B
b0 G
b0 M
b0 $
b0 9
b0 Y
b11100100 8
b11100100 <
b11100100 N
b11100100 T
b101 H
11
b11 *
b11 O
b11 [
b11 j
b11100100 +
b11100100 ;
b11100100 k
b10 >
b10 D
b100011 =
b100011 F
b100011 J
b0 h
b110 g
b11110 f
b0 4
b0 Z
b0 `
b0 o
b11011110010000000100011 )
b11011110010000000100011 R
b11011110010000000100011 n
b1000100 /
b1000100 \
b1000100 d
b1000100 .
b1000100 X
b1000100 ^
b1000100 b
b1000000 ,
b1000000 ]
b1000000 _
b1000000 0
b1000000 S
b1000000 a
b1000000 c
b1000000 e
1!
#320
0!
#330
0#
07
b1 6
b1 :
b1 C
b1 I
b10 H
1'
b11 3
b11 A
b11 L
b11 m
1-
b1 B
b1 G
b1 M
b100 8
b100 <
b100 N
b100 T
01
12
b0 *
b0 O
b0 [
b0 j
b100 +
b100 ;
b100 k
b0 $
b0 9
b0 Y
b1111110 ?
b1111110 E
b111 >
b111 D
b1101111 =
b1101111 F
b1101111 J
b1 h
b11001 g
b11111 f
b11111111111111111111111111011000 4
b11111111111111111111111111011000 Z
b11111111111111111111111111011000 `
b11111111111111111111111111011000 o
b1001000 &
b1001000 W
b1001000 i
b11111101100111111111000011101111 )
b11111101100111111111000011101111 R
b11111101100111111111000011101111 n
b111 (
b111 P
b111 U
b11100 /
b11100 \
b11100 d
b1001000 .
b1001000 X
b1001000 ^
b1001000 b
b11100 ,
b11100 ]
b11100 _
b1000100 0
b1000100 S
b1000100 a
b1000100 c
b1000100 e
1!
#340
0!
#350
bx (
bx P
bx U
b10 3
b10 A
b10 L
b10 m
0'
0-
b10100 $
b10100 9
b10100 Y
b11111111111111111111111111101101 8
b11111111111111111111111111101101 <
b11111111111111111111111111101101 N
b11111111111111111111111111101101 T
b0 H
15
02
b10100 *
b10100 O
b10100 [
b10100 j
b1 +
b1 ;
b1 k
b1 ?
b1 E
b0 >
b0 D
b1100011 =
b1100011 F
b1100011 J
b1100 h
b101 g
b10010 f
b101100 4
b101100 Z
b101100 `
b101100 o
b100000 &
b100000 W
b100000 i
b10010110010000011001100011 )
b10010110010000011001100011 R
b10010110010000011001100011 n
b100000 /
b100000 \
b100000 d
b100000 .
b100000 X
b100000 ^
b100000 b
b1001000 ,
b1001000 ]
b1001000 _
b11100 0
b11100 S
b11100 a
b11100 c
b11100 e
1!
#360
0!
